nessus_file_reader/__about__.py
nessus_file_reader/__init__.py
nessus_file_reader/__main__.py
nessus_file_reader/_version.py
nessus_file_reader/utilities.py
nessus_file_reader/file/__init__.py
nessus_file_reader/file/file.py
nessus_file_reader/host/__init__.py
nessus_file_reader/host/host.py
nessus_file_reader/plugin/__init__.py
nessus_file_reader/plugin/plugin.py
nessus_file_reader/scan/__init__.py
nessus_file_reader/scan/scan.py
nessus_file_reader-0.7.2.dist-info/licenses/LICENSE
nessus_file_reader-0.7.2.dist-info/METADATA
nessus_file_reader-0.7.2.dist-info/WHEEL
nessus_file_reader-0.7.2.dist-info/entry_points.txt
nessus_file_reader-0.7.2.dist-info/top_level.txt
nessus_file_reader-0.7.2.dist-info/RECORD
