Metadata-Version: 2.4
Name: nessus_file_reader
Version: 0.7.2
Summary: nessus file reader (NFR) by LimberDuck is a CLI tool and python module created to quickly parse nessus files containing the results of scans performed by Tenable Nessus and Tenable Security Center.
Home-page: https://github.com/LimberDuck/nessus-file-reader
Author: Damian Krawczyk
Author-email: damian.krawczyk@limberduck.org
License: GPLv3
Classifier: Programming Language :: Python :: 3.13
Classifier: Programming Language :: Python :: 3.12
Classifier: Programming Language :: Python :: 3.11
Classifier: Programming Language :: Python :: 3.10
Classifier: License :: OSI Approved :: GNU General Public License v3 (GPLv3)
Classifier: Operating System :: OS Independent
Classifier: Development Status :: 4 - Beta
Classifier: Environment :: Console
License-File: LICENSE
Requires-Dist: click>=8.2.1
Requires-Dist: tabulate>=0.9.0
Requires-Dist: jmespath>=1.0.1
Requires-Dist: requests>=2.32.5
Requires-Dist: packaging>=25.0
Dynamic: author
Dynamic: author-email
Dynamic: classifier
Dynamic: description
Dynamic: description-content-type
Dynamic: home-page
Dynamic: license
Dynamic: license-file
Dynamic: requires-dist
Dynamic: summary
